ci_rtpc/Enums.py
ci_rtpc/__init__.py
ci_rtpc/kunyi_hil_test.py
ci_rtpc/kunyi_mrt.py
ci_rtpc/kunyi_project.py
ci_rtpc/kunyi_util.py
ci_rtpc/libmrt.so
ci_rtpc/mrt.dll
ci_rtpc/mrt_strunctures.py
ci_rtpc/signal_daq.py
ci_rtpc-1.0.3.dist-info/LICENSE
ci_rtpc-1.0.3.dist-info/METADATA
ci_rtpc-1.0.3.dist-info/WHEEL
ci_rtpc-1.0.3.dist-info/top_level.txt
ci_rtpc-1.0.3.dist-info/RECORD
