Metadata-Version: 2.1
Name: ci-rtpc
Version: 1.0.3
Summary: ky ci rtpc auto test
Home-page: 
Author: lyl
Author-email: lyulei66@163.com
Classifier: Programming Language :: Python :: 3
Classifier: License :: OSI Approved :: MIT License
Classifier: Operating System :: OS Independent
Requires-Python: >=3.6
License-File: LICENSE
